{
  "name": "Melvin Jones",
  "age": 40,
  "address": {
    "street": "Erada Way",
    "city": "Befgewkop",
    "state": "RI",
    "zip": "24906"
  },
  "contact": {
    "phone": "(858) 645-6191",
    "servicePhone": "800822442"
  },
  "birthday": "2005-08-05T23:17:39.366Z",
  "ip": "251.121.180.13",
  "foo": "bar",
  "profile": {
    "about": "Cec jamawa uslop vem guhtoso bomgu giogusos orvef haccoz pigoevi bahilic ga uje viavamik enorizu kohvomih. Hoggeca wa ankipo cel cijvub wawisra winvi majno una nium ike je. Soj uz hirtuppi keput pecofbah ibalos ruckusvu ulape mac azcu soj mopaki bop abowed pijko ewmo ru. Zielupis midnipew vaw jor cubebaw kizebcif cew accon zafnih ojfepav fap ce hemcehenu nar uka. Pozima jesacer ozikogo ar hafgi zinael lu teniha zallov tanure namuvuki voh se iwe wo epmek kac owohoc.",
    "bio": "Norom su efope sone cuwwihit vuf rosa wuas suf la vu soolara ze bajogi emewi. Ma lok ecrew gizretac cedij uweju ni vihpegjon sajob sivabdut navele utdifcu. Mumu urruepa mazzoanu mihfeb kununu mon la lawfolgi vi funci isilu idu len cizes des juzivwo cef wapfi. Zi ja mulehdi zo sa rez fapzela lofjife oh semozjem vetuz zodkogbub uh verba jucsahalo rugsavo kevnolmoh gu. Guw wod tebekjim cupalka fek ratpewboj hosuspa baffakak hiwsadwob kebcidu ic iwede so loehe ginwam fu. Vose lawezru fera mizeje dipa kiz bapu kiuste parej ra jocec liwcek belliv cavo."
  },
  "apiKey": "e158ea492dddf60e67066b7493875d40ae17b91052066c5c456e8da82c719c73",
  "currency": {
    "code": "HNL",
    "name": "Honduras Lempira"
  }
}