{
  "name": "Calvin Lopez",
  "age": 27,
  "address": {
    "street": "Pikajo Road",
    "city": "Fizoheege",
    "state": "DC",
    "zip": "42211"
  },
  "contact": {
    "phone": "(823) 606-5757",
    "servicePhone": "800951318"
  },
  "birthday": "1960-03-28T13:39:37.041Z",
  "ip": "86.2.5.246",
  "foo": "bar",
  "profile": {
    "about": "Ridvi pipuwom vol lihi zu sesun afviku ji muvoseku wo bot ize fiavizo opomo ta. Ziaviep wotmod vaebdu kosdiino cofemu wi zotelda jopupeh uso lisamo opo jezedkom zeeho oflijrik dumpa tadif. Nocod pup powu uwipowaw niz sitkonmik zavjucon sovosavi vefbakab fo gotaz alavevuf. Odoke jakso lohuha jibaspe rudi pifoj leneriwa ja awolec sa kidkesu vonoevu. Bu wu gobaw jakorap werulhah epe jocil ar usi jew golab mu dezomamew. Updaj siw guvla ewepevoz moco guifipe fuildo huw mugvokir za nikjud cujtuvja gulwoc dejvekete neoghur ebidumoh saw. Huorozi sab jobo ad lijte cuwofip paj ragapir abe ki ravowpa culse husof gi zakdagul.",
    "bio": "Wuv juwubevo ez mohiveoca ucirohjo ebu nep at zelfu je up huljil. Cace hivu kouziwi molodu ve enafekcu budwitip nocwup sapbut hapur nodu dap. Mo aw buc merohen zojzow vo hud oro soba ujiigi lupfokot onu mi fuzom notadu matgatep oga. Getfuw betiki wenmudgi bosbu aceva vida ir kiubze tite setebza utve fujuvvin avihemnal opo me. Fegen kazek nuoha ajiecaoko mi holubtap sefkuh moj jasiscem kawuc di hunilje uf rotivapin bufi roab rapehni. Nof nogop buwgasoke nosipfen ewevesoc ra wok reovoki gahlate lo tutjaem borepka pugewe nerawsi fasvicvu cias jerif."
  },
  "apiKey": "b5ba9367f451df59badb151517e21826cbf99d5851d5cee9c36f5a12d97c7c36",
  "currency": {
    "code": "BTN",
    "name": "Bhutan Ngultrum"
  }
}